svg/__init__.py
svg/elements.py
svg/elements/__init__.py
svg/elements/svg_elements.py
svg.elements-0.7.7.dist-info/LICENSE
svg.elements-0.7.7.dist-info/METADATA
svg.elements-0.7.7.dist-info/WHEEL
svg.elements-0.7.7.dist-info/top_level.txt
svg.elements-0.7.7.dist-info/zip-safe
svg.elements-0.7.7.dist-info/RECORD
